Workbook

Sheet 主站
A1: # | B1: Title | C1: 标题 | D1: 链接 | E1: 是否会员 | F1: 分类 | G1: 等级 | H1: 进阶等级 | I1: 难度 | J1: 竞赛
A2: 1 | B2: Two Sum | C2: 两数之和 | D2: https://leetcode.cn/problems/two-sum/ | E2: 0 | F2: Algorithms | G2: 2 | H2: 2 | I2: Easy
A3: 2 | B3: Add Two Numbers | C3: 两数相加 | D3: https://leetcode.cn/problems/add-two-numbers/ | E3: 0 | F3: Algorithms | G3: 3 | H3: 0 | I3: Medium
A4: 3 | B4: Longest Substring Without Repeating Characters | C4: 无重复字符的最长子串 | D4: https://leetcode.cn/problems/longest-substring-without-repeating-characters/ | E4: 0 | F4: Algorithms | G4: 5 | H4: 0 | I4: Medium
A5: 4 | B5: Median of Two Sorted Arrays | C5: 寻找两个正序数组的中位数 | D5: https://leetcode.cn/problems/median-of-two-sorted-arrays/ | E5: 0 | F5: Algorithms | G5: 8 | H5: 0 | I5: Hard
A6: 5 | B6: Longest Palindromic Substring | C6: 最长回文子串 | D6: https://leetcode.cn/problems/longest-palindromic-substring/ | E6: 0 | F6: Algorithms | G6: 5 | H6: 0 | I6: Medium
A7: 6 | B7: Zigzag Conversion | C7: Z 字形变换 | D7: https://leetcode.cn/problems/zigzag-conversion/ | E7: 0 | F7: Algorithms | G7: 4 | H7: 0 | I7: Medium
A8: 7 | B8: Reverse Integer | C8: 整数反转 | D8: https://leetcode.cn/problems/reverse-integer/ | E8: 0 | F8: Algorithms | G8: 5 | H8: 0 | I8: Medium
A9: 8 | B9: String to Integer (atoi) | C9: 字符串转换整数 (atoi) | D9: https://leetcode.cn/problems/string-to-integer-atoi/ | E9: 0 | F9: Algorithms | G9: 6 | H9: 0 | I9: Medium
A10: 9 | B10: Palindrome Number | C10: 回文数 | D10: https://leetcode.cn/problems/palindrome-number/ | E10: 0 | F10: Algorithms | G10: 2 | H10: 3 | I10: Easy
A11: 10 | B11: Regular Expression Matching | C11: 正则表达式匹配 | D11: https://leetcode.cn/problems/regular-expression-matching/ | E11: 0 | F11: Algorithms | G11: 8 | H11: 0 | I11: Hard
A12: 11 | B12: Container With Most Water | C12: 盛最多水的容器 | D12: https://leetcode.cn/problems/container-with-most-water/ | E12: 0 | F12: Algorithms | G12: 4 | H12: 0 | I12: Medium
A13: 12 | B13: Integer to Roman | C13: 整数转罗马数字 | D13: https://leetcode.cn/problems/integer-to-roman/ | E13: 0 | F13: Algorithms | G13: 3 | H13: 0 | I13: Medium
... A386: 385 | B386: Mini Parser | C386: 迷你语法分析器 | D386: https://leetcode.cn/problems/mini-parser/ | E386: 0 | F386: Algorithms | G386: 6 | H386: 0 | I386: Medium
A387: 386 | B387: Lexicographical Numbers | C387: 字典序排数 | D387: https://leetcode.cn/problems/lexicographical-numbers/ | E387: 0 | F387: Algorithms | G387: 6 | H387: 0 | I387: Medium | J387: Warm Up Contest 1 Problem 1
A388: 387 | B388: First Unique Character in a String | C388: 字符串中的第一个唯一字符 | D388: https://leetcode.cn/problems/first-unique-character-in-a-string/ | E388: 0 | F388: Algorithms | G388: 3 | H388: 0 | I388: Easy | J388: Warm Up Contest 1 Problem 2
A389: 388 | B389: Longest Absolute File Path | C389: 文件的最长绝对路径 | D389: https://leetcode.cn/problems/longest-absolute-file-path/ | E389: 0 | F389: Algorithms | G389: 7 | H389: 0 | I389: Medium | J389: Warm Up Contest 1 Problem 3
A390: 389 | B390: Find the Difference | C390: 找不同 | D390: https://leetcode.cn/problems/find-the-difference/ | E390: 0 | F390: Algorithms | G390: 2 | H390: 0 | I390: Easy | J390: Weekly Contest 2 Problem 1
A391: 390 | B391: Elimination Game | C391: 消除游戏 | D391: https://leetcode.cn/problems/elimination-game/ | E391: 0 | F391: Algorithms | G391: 6 | H391: 0 | I391: Medium | J391: Weekly Contest 2 Problem 2
A392: 391 | B392: Perfect Rectangle | C392: 完美矩形 | D392: https://leetcode.cn/problems/perfect-rectangle/ | E392: 0 | F392: Algorithms | G392: 8 | H392: 0 | I392: Hard | J392: Weekly Contest 2 Problem 3
A393: 392 | B393: Is Subsequence | C393: 判断子序列 | D393: https://leetcode.cn/problems/is-subsequence/ | E393: 0 | F393: Algorithms | G393: 3 | H393: 7 | I393: Easy | J393: Weekly Contest 3 Problem 1
A394: 393 | B394: UTF-8 Validation | C394: UTF-8 编码验证 | D394: https://leetcode.cn/problems/utf-8-validation/ | E394: 0 | F394: Algorithms | G394: 4 | H394: 0 | I394: Medium | J394: Weekly Contest 3 Problem 2
A395: 394 | B395: Decode String | C395: 字符串解码 | D395: https://leetcode.cn/problems/decode-string/ | E395: 0 | F395: Algorithms | G395: 6 | H395: 0 | I395: Medium | J395: Weekly Contest 3 Problem 3
A396: 395 | B396: Longest Substring with At Least K Repeating Characters | C396: 至少有K个重复字符的最长子串 | D396: https://leetcode.cn/problems/longest-substring-with-at-least-k-repeating-characters/ | E396: 0 | F396: Algorithms | G396: 6 | H396: 0 | I396: Medium | J396: Weekly Contest 3 Problem 4
A397: 396 | B397: Rotate Function | C397: 旋转函数 | D397: https://leetcode.cn/problems/rotate-function/ | E397: 0 | F397: Algorithms | G397: 5 | H397: 0 | I397: Medium | J397: Weekly Contest 4 Problem 1
A398: 397 | B398: Integer Replacement | C398: 整数替换 | D398: https://leetcode.cn/problems/integer-replacement/ | E398: 0 | F398: Algorithms | G398: 5 | H398: 0 | I398: Medium | J398: Weekly Contest 4 Problem 2
... A412: 411 | B412: Minimum Unique Word Abbreviation | C412: 最短独占单词缩写 | D412: https://leetcode.cn/problems/minimum-unique-word-abbreviation/ | E412: 1 | F412: Algorithms | G412: 6 | H412: 0 | I412: Hard | J412: Weekly Contest 7 Problem 4
A413: 412 | B413: Fizz Buzz | C413: Fizz Buzz | D413: https://leetcode.cn/problems/fizz-buzz/ | E413: 0 | F413: Algorithms | G413: 2 | H413: 0 | I413: Easy
A414: 413 | B414: Arithmetic Slices | C414: 等差数列划分 | D414: https://leetcode.cn/problems/arithmetic-slices/ | E414: 0 | F414: Algorithms | G414: 4 | H414: 0 | I414: Medium
A415: 414 | B415: Third Maximum Number | C415: 第三大的数 | D415: https://leetcode.cn/problems/third-maximum-number/ | E415: 0 | F415: Algorithms | G415: 3 | H415: 3 | I415: Easy
A416: 415 | B416: Add Strings | C416: 字符串相加 | D416: https://leetcode.cn/problems/add-strings/ | E416: 0 | F416: Algorithms | G416: 3 | H416: 0 | I416: Easy | J416: Weekly Contest 8 Problem 1
A417: 416 | B417: Partition Equal Subset Sum | C417: 分割等和子集 | D417: https://leetcode.cn/problems/partition-equal-subset-sum/ | E417: 0 | F417: Algorithms | G417: 5 | H417: 0 | I417: Medium | J417: Weekly Contest 8 Problem 2
A418: 417 | B418: Pacific Atlantic Water Flow | C418: 太平洋大西洋水流问题 | D418: https://leetcode.cn/problems/pacific-atlantic-water-flow/ | E418: 0 | F418: Algorithms | G418: 5 | H418: 0 | I418: Medium | J418: Weekly Contest 8 Problem 3
A419: 418 | B419: Sentence Screen Fitting | C419: 屏幕可显示句子的数量 | D419: https://leetcode.cn/problems/sentence-screen-fitting/ | E419: 1 | F419: Algorithms | G419: 7 | H419: 0 | I419: Medium | J419: Weekly Contest 8 Problem 4
A420: 419 | B420: Battleships in a Board | C420: 甲板上的战舰 | D420: https://leetcode.cn/problems/battleships-in-a-board/ | E420: 0 | F420: Algorithms | G420: 4 | H420: 4 | I420: Medium
A421: 420 | B421: Strong Password Checker | C421: 强密码检验器 | D421: https://leetcode.cn/problems/strong-password-checker/ | E421: 0 | F421: Algorithms | G421: 10 | H421: 0 | I421: Hard
A422: 421 | B422: Maximum XOR of Two Numbers in an Array | C422: 数组中两个数的最大异或值 | D422: https://leetcode.cn/problems/maximum-xor-of-two-numbers-in-an-array/ | E422: 0 | F422: Algorithms | G422: 8 | H422: 0 | I422: Medium
A423: 422 | B423: Valid Word Square | C423: 有效的单词方块 | D423: https://leetcode.cn/problems/valid-word-square/ | E423: 1 | F423: Algorithms | G423: 4 | H423: 0 | I423: Easy | J423: Weekly Contest 9 Problem 1
A424: 423 | B424: Reconstruct Original Digits from English | C424: 从英文中重建数字 | D424: https://leetcode.cn/problems/reconstruct-original-digits-from-english/ | E424: 0 | F424: Algorithms | G424: 4 | H424: 0 | I424: Medium | J424: Weekly Contest 9 Problem 2
A425: 424 | B425: Longest Repeating Character Replacement | C425: 替换后的最长重复字符 | D425: https://leetcode.cn/problems/longest-repeating-character-replacement/ | E425: 0 | F425: Algorithms | G425: 6 | H425: 0 | I425: Medium | J425: Weekly Contest 9 Problem 3
A426: 425 | B426: Word Squares | C426: 单词方块 | D426: https://leetcode.cn/problems/word-squares/ | E426: 1 | F426: Algorithms | G426: 9 | H426: 0 | I426: Hard | J426: Weekly Contest 9 Problem 4
A427: 426 | B427: Convert Binary Search Tree to Sorted Doubly Linked List | C427: 将二叉搜索树转化为排序的双向链表 | D427: https://leetcode.cn/problems/convert-binary-search-tree-to-sorted-doubly-linked-list/ | E427: 1 | F427: Algorithms | G427: 4 | H427: 0 | I427: Medium
A428: 427 | B428: Construct Quad Tree | C428: 建立四叉树 | D428: https://leetcode.cn/problems/construct-quad-tree/ | E428: 0 | F428: Algorithms | G428: 5 | H428: 0 | I428: Medium
A429: 428 | B429: Serialize and Deserialize N-ary Tree | C429: 序列化和反序列化 N 叉树 | D429: https://leetcode.cn/problems/serialize-and-deserialize-n-ary-tree/ | E429: 1 | F429: Algorithms | G429: 9 | H429: 0 | I429: Hard
A430: 429 | B430: N-ary Tree Level Order Traversal | C430: N叉树的层序遍历 | D430: https://leetcode.cn/problems/n-ary-tree-level-order-traversal/ | E430: 0 | F430: Algorithms | G430: 4 | H430: 0 | I430: Medium
A431: 430 | B431: Flatten a Multilevel Doubly Linked List | C431: 扁平化多级双向链表 | D431: https://leetcode.cn/problems/flatten-a-multilevel-doubly-linked-list/ | E431: 0 | F431: Algorithms | G431: 7 | H431: 0 | I431: Medium
A432: 431 | B432: Encode N-ary Tree to Binary Tree | C432: 将 N 叉树编码为二叉树 | D432: https://leetcode.cn/problems/encode-n-ary-tree-to-binary-tree/ | E432: 1 | F432: Algorithms | G432: 9 | H432: 0 | I432: Hard
A433: 432 | B433: All O`one Data Structure | C433: 全 O(1) 的数据结构 | D433: https://leetcode.cn/problems/all-oone-data-structure/ | E433: 0 | F433: Algorithms | G433: 10 | H433: 0 | I433: Hard
A434: 433 | B434: Minimum Genetic Mutation | C434: 最小基因变化 | D434: https://leetcode.cn/problems/minimum-genetic-mutation/ | E434: 0 | F434: Algorithms | G434: 5 | H434: 0 | I434: Medium
A435: 434 | B435: Number of Segments in a String | C435: 字符串中的单词数 | D435: https://leetcode.cn/problems/number-of-segments-in-a-string/ | E435: 0 | F435: Algorithms | G435: 3 | H435: 0 | I435: Easy | J435: Weekly Contest 11 Problem 1
A436: 435 | B436: Non-overlapping Intervals | C436: 无重叠区间 | D436: https://leetcode.cn/problems/non-overlapping-intervals/ | E436: 0 | F436: Algorithms | G436: 6 | H436: 0 | I436: Medium | J436: Smarking Algorithm Contest 2 Problem 1
A437: 436 | B437: Find Right Interval | C437: 寻找右区间 | D437: https://leetcode.cn/problems/find-right-interval/ | E437: 0 | F437: Algorithms | G437: 6 | H437: 0 | I437: Medium | J437: Smarking Algorithm Contest 2 Problem 2
A438: 437 | B438: Path Sum III | C438: 路径总和 III | D438: https://leetcode.cn/problems/path-sum-iii/ | E438: 0 | F438: Algorithms | G438: 5 | H438: 0 | I438: Medium | J438: Smarking Algorithm Contest Problem 1
A439: 438 | B439: Find All Anagrams in a String | C439: 找到字符串中所有字母异位词 | D439: https://leetcode.cn/problems/find-all-anagrams-in-a-string/ | E439: 0 | F439: Algorithms | G439: 4 | H439: 0 | I439: Medium | J439: Smarking Algorithm Contest Problem 2
A440: 439 | B440: Ternary Expression Parser | C440: 三元表达式解析器 | D440: https://leetcode.cn/problems/ternary-expression-parser/ | E440: 1 | F440: Algorithms | G440: 6 | H440: 0 | I440: Medium | J440: Smarking Algorithm Contest Problem 3
A441: 440 | B441: K-th Smallest in Lexicographical Order | C441: 字典序的第K小数字 | D441: https://leetcode.cn/problems/k-th-smallest-in-lexicographical-order/ | E441: 0 | F441: Algorithms | G441: 8 | H441: 0 | I441: Hard | J441: Smarking Algorithm Contest Problem 4
A442: 441 | B442: Arranging Coins | C442: 排列硬币 | D442: https://leetcode.cn/problems/arranging-coins/ | E442: 0 | F442: Algorithms | G442: 3 | H442: 0 | I442: Easy | J442: Smarking Algorithm Contest 2 Problem 3
A443: 442 | B443: Find All Duplicates in an Array | C443: 数组中重复的数据 | D443: https://leetcode.cn/problems/find-all-duplicates-in-an-array/ | E443: 0 | F443: Algorithms | G443: 6 | H443: 0 | I443: Medium
A444: 443 | B444: String Compression | C444: 压缩字符串 | D444: https://leetcode.cn/problems/string-compression/ | E444: 0 | F444: Algorithms | G444: 4 | H444: 0 | I444: Medium | J444: Weekly Contest 56 Problem 2
A445: 444 | B445: Sequence Reconstruction | C445: 序列重建 | D445: https://leetcode.cn/problems/sequence-reconstruction/ | E445: 1 | F445: Algorithms | G445: 7 | H445: 0 | I445: Medium | J445: Smarking Algorithm Contest 2 Problem 4
A446: 445 | B446: Add Two Numbers II | C446: 两数相加 II | D446: https://leetcode.cn/problems/add-two-numbers-ii/ | E446: 0 | F446: Algorithms | G446: 4 | H446: 4 | I446: Medium
A447: 446 | B447: Arithmetic Slices II - Subsequence | C447: 等差数列划分 II - 子序列 | D447: https://leetcode.cn/problems/arithmetic-slices-ii-subsequence/ | E447: 0 | F447: Algorithms | G447: 8 | H447: 0 | I447: Hard | J447: Smarking Algorithm Contest 3 Problem 4
A448: 447 | B448: Number of Boomerangs | C448: 回旋镖的数量 | D448: https://leetcode.cn/problems/number-of-boomerangs/ | E448: 0 | F448: Algorithms | G448: 4 | H448: 0 | I448: Medium | J448: Smarking Algorithm Contest 3 Problem 2
A449: 448 | B449: Find All Numbers Disappeared in an Array | C449: 找到所有数组中消失的数字 | D449: https://leetcode.cn/problems/find-all-numbers-disappeared-in-an-array/ | E449: 0 | F449: Algorithms | G449: 2 | H449: 6 | I449: Easy
A450: 449 | B450: Serialize and Deserialize BST | C450: 序列化和反序列化二叉搜索树 | D450: https://leetcode.cn/problems/serialize-and-deserialize-bst/ | E450: 0 | F450: Algorithms | G450: 6 | H450: 0 | I450: Medium
A451: 450 | B451: Delete Node in a BST | C451: 删除二叉搜索树中的节点 | D451: https://leetcode.cn/problems/delete-node-in-a-bst/ | E451: 0 | F451: Algorithms | G451: 5 | H451: 5 | I451: Medium
A452: 451 | B452: Sort Characters By Frequency | C452: 根据字符出现频率排序 | D452: https://leetcode.cn/problems/sort-characters-by-frequency/ | E452: 0 | F452: Algorithms | G452: 3 | H452: 0 | I452: Medium
A453: 452 | B453: Minimum Number of Arrows to Burst Balloons | C453: 用最少数量的箭引爆气球 | D453: https://leetcode.cn/problems/minimum-number-of-arrows-to-burst-balloons/ | E453: 0 | F453: Algorithms | G453: 6 | H453: 0 | I453: Medium | J453: Smarking Algorithm Contest 3 Problem 3
A454: 453 | B454: Minimum Moves to Equal Array Elements | C454: 最小移动次数使数组元素相等 | D454: https://leetcode.cn/problems/minimum-moves-to-equal-array-elements/ | E454: 0 | F454: Algorithms | G454: 3 | H454: 0 | I454: Medium | J454: Smarking Algorithm Contest 3 Problem 1
A455: 454 | B455: 4Sum II | C455: 四数相加 II | D455: https://leetcode.cn/problems/4sum-ii/ | E455: 0 | F455: Algorithms | G455: 6 | H455: 0 | I455: Medium | J455: Smarking Algorithm Contest 4 Problem 3
A456: 455 | B456: Assign Cookies | C456: 分发饼干 | D456: https://leetcode.cn/problems/assign-cookies/ | E456: 0 | F456: Algorithms | G456: 3 | H456: 0 | I456: Easy | J456: Smarking Algorithm Contest 4 Problem 1
A457: 456 | B457: 132 Pattern | C457: 132模式 | D457: https://leetcode.cn/problems/132-pattern/ | E457: 0 | F457: Algorithms | G457: 6 | H457: 0 | I457: Medium | J457: Smarking Algorithm Contest 4 Problem 4
A458: 457 | B458: Circular Array Loop | C458: 环形数组是否存在循环 | D458: https://leetcode.cn/problems/circular-array-loop/ | E458: 0 | F458: Algorithms | G458: 5 | H458: 7 | I458: Medium
A459: 458 | B459: Poor Pigs | C459: 可怜的小猪 | D459: https://leetcode.cn/problems/poor-pigs/ | E459: 0 | F459: Algorithms | G459: 8 | H459: 0 | I459: Hard
A460: 459 | B460: Repeated Substring Pattern | C460: 重复的子字符串 | D460: https://leetcode.cn/problems/repeated-substring-pattern/ | E460: 0 | F460: Algorithms | G460: 3 | H460: 0 | I460: Easy | J460: Smarking Algorithm Contest 4 Problem 2
A461: 460 | B461: LFU Cache | C461: LFU 缓存 | D461: https://leetcode.cn/problems/lfu-cache/ | E461: 0 | F461: Algorithms | G461: 9 | H461: 0 | I461: Hard
A462: 461 | B462: Hamming Distance | C462: 汉明距离 | D462: https://leetcode.cn/problems/hamming-distance/ | E462: 0 | F462: Algorithms | G462: 2 | H462: 0 | I462: Easy | J462: Weekly Contest 13 Problem 1
A463: 462 | B463: Minimum Moves to Equal Array Elements II | C463: 最小操作次数使数组元素相等 II | D463: https://leetcode.cn/problems/minimum-moves-to-equal-array-elements-ii/ | E463: 0 | F463: Algorithms | G463: 5 | H463: 0 | I463: Medium | J463: Weekly Contest 10 Problem 3
A464: 463 | B464: Island Perimeter | C464: 岛屿的周长 | D464: https://leetcode.cn/problems/island-perimeter/ | E464: 0 | F464: Algorithms | G464: 4 | H464: 0 | I464: Easy | J464: Weekly Contest 10 Problem 1
A465: 464 | B465: Can I Win | C465: 我能赢吗 | D465: https://leetcode.cn/problems/can-i-win/ | E465: 0 | F465: Algorithms | G465: 8 | H465: 0 | I465: Medium | J465: Weekly Contest 10 Problem 2
A466: 465 | B466: Optimal Account Balancing | C466: 最优账单平衡 | D466: https://leetcode.cn/problems/optimal-account-balancing/ | E466: 1 | F466: Algorithms | G466: 8 | H466: 0 | I466: Hard | J466: Weekly Contest 10 Problem 4
A467: 466 | B467: Count The Repetitions | C467: 统计重复个数 | D467: https://leetcode.cn/problems/count-the-repetitions/ | E467: 0 | F467: Algorithms | G467: 8 | H467: 0 | I467: Hard | J467: Weekly Contest 11 Problem 4
A468: 467 | B468: Unique Substrings in Wraparound String | C468: 环绕字符串中唯一的子字符串 | D468: https://leetcode.cn/problems/unique-substrings-in-wraparound-string/ | E468: 0 | F468: Algorithms | G468: 5 | H468: 0 | I468: Medium | J468: Weekly Contest 11 Problem 3
A469: 468 | B469: Validate IP Address | C469: 验证IP地址 | D469: https://leetcode.cn/problems/validate-ip-address/ | E469: 0 | F469: Algorithms | G469: 4 | H469: 0 | I469: Medium | J469: Weekly Contest 12 Problem 2
A470: 469 | B470: Convex Polygon | C470: 凸多边形 | D470: https://leetcode.cn/problems/convex-polygon/ | E470: 1 | F470: Algorithms | G470: 7 | H470: 0 | I470: Medium | J470: Weekly Contest 11 Problem 2
A471: 470 | B471: Implement Rand10() Using Rand7() | C471: 用 Rand7() 实现 Rand10() | D471: https://leetcode.cn/problems/implement-rand10-using-rand7/ | E471: 0 | F471: Algorithms | G471: 5 | H471: 10 | I471: Medium
A472: 471 | B472: Encode String with Shortest Length | C472: 编码最短长度的字符串 | D472: https://leetcode.cn/problems/encode-string-with-shortest-length/ | E472: 1 | F472: Algorithms | G472: 9 | H472: 0 | I472: Hard | J472: Weekly Contest 12 Problem 4
A473: 472 | B473: Concatenated Words | C473: 连接词 | D473: https://leetcode.cn/problems/concatenated-words/ | E473: 0 | F473: Algorithms | G473: 7 | H473: 0 | I473: Hard | J473: Weekly Contest 13 Problem 4
A474: 473 | B474: Matchsticks to Square | C474: 火柴拼正方形 | D474: https://leetcode.cn/problems/matchsticks-to-square/ | E474: 0 | F474: Algorithms | G474: 5 | H474: 0 | I474: Medium | J474: Weekly Contest 13 Problem 3
A475: 474 | B475: Ones and Zeroes | C475: 一和零 | D475: https://leetcode.cn/problems/ones-and-zeroes/ | E475: 0 | F475: Algorithms | G475: 6 | H475: 0 | I475: Medium | J475: Weekly Contest 12 Problem 3
A476: 475 | B476: Heaters | C476: 供暖器 | D476: https://leetcode.cn/problems/heaters/ | E476: 0 | F476: Algorithms | G476: 5 | H476: 0 | I476: Medium | J476: Weekly Contest 12 Problem 1
A477: 476 | B477: Number Complement | C477: 数字的补数 | D477: https://leetcode.cn/problems/number-complement/ | E477: 0 | F477: Algorithms | G477: 3 | H477: 0 | I477: Easy | J477: Weekly Contest 14 Problem 1
A478: 477 | B478: Total Hamming Distance | C478: 汉明距离总和 | D478: https://leetcode.cn/problems/total-hamming-distance/ | E478: 0 | F478: Algorithms | G478: 4 | H478: 0 | I478: Medium | J478: Weekly Contest 13 Problem 2
A479: 478 | B479: Generate Random Point in a Circle | C479: 在圆内随机生成点 | D479: https://leetcode.cn/problems/generate-random-point-in-a-circle/ | E479: 0 | F479: Algorithms | G479: 7 | H479: 0 | I479: Medium
A480: 479 | B480: Largest Palindrome Product | C480: 最大回文数乘积 | D480: https://leetcode.cn/problems/largest-palindrome-product/ | E480: 0 | F480: Algorithms | G480: 8 | H480: 0 | I480: Hard
A481: 480 | B481: Sliding Window Median | C481: 滑动窗口中位数 | D481: https://leetcode.cn/problems/sliding-window-median/ | E481: 0 | F481: Algorithms | G481: 9 | H481: 0 | I481: Hard | J481: Weekly Contest 14 Problem 4
A482: 481 | B482: Magical String | C482: 神奇字符串 | D482: https://leetcode.cn/problems/magical-string/ | E482: 0 | F482: Algorithms | G482: 5 | H482: 0 | I482: Medium | J482: Weekly Contest 14 Problem 2
A483: 482 | B483: License Key Formatting | C483: 密钥格式化 | D483: https://leetcode.cn/problems/license-key-formatting/ | E483: 0 | F483: Algorithms | G483: 3 | H483: 0 | I483: Easy | J483: Weekly Contest 14 Problem 3
A484: 483 | B484: Smallest Good Base | C484: 最小好进制 | D484: https://leetcode.cn/problems/smallest-good-base/ | E484: 0 | F484: Algorithms | G484: 10 | H484: 0 | I484: Hard | J484: Weekly Contest 16B Problem 3
A485: 484 | B485: Find Permutation | C485: 寻找排列 | D485: https://leetcode.cn/problems/find-permutation/ | E485: 1 | F485: Algorithms | G485: 7 | H485: 0 | I485: Medium | J485: Weekly Contest 16A Problem 1
...

Sheet LCP
A1: # | B1: 标题 | C1: 链接 | D1: 是否会员 | E1: 分类 | F1: 等级 | G1: 进阶等级 | H1: 难度 | I1: 竞赛
A2: LCP 01 | B2: 猜数字 | C2: https://leetcode.cn/problems/guess-numbers/ | D2: 0 | E2: Algorithms | F2: 1 | G2: 0 | H2: Easy | I2: LCP 2019 Fall Problem 1
A3: LCP 02 | B3: 分式化简 | C3: https://leetcode.cn/problems/deep-dark-fraction/ | D3: 0 | E3: Algorithms | F3: 4 | G3: 0 | H3: Easy | I3: LCP 2019 Fall Problem 2
A4: LCP 03 | B4: 机器人大冒险 | C4: https://leetcode.cn/problems/programmable-robot/ | D4: 0 | E4: Algorithms | F4: 6 | G4: 0 | H4: Medium | I4: LCP 2019 Fall Problem 3
A5: LCP 04 | B5: 覆盖 | C5: https://leetcode.cn/problems/broken-board-dominoes/ | D5: 0 | E5: Algorithms | F5: 8 | G5: 0 | H5: Hard | I5: LCP 2019 Fall Problem 4
A6: LCP 05 | B6: 发 LeetCoin | C6: https://leetcode.cn/problems/coin-bonus/ | D6: 0 | E6: Algorithms | F6: 10 | G6: 0 | H6: Hard | I6: LCP 2019 Fall Problem 5
A7: LCP 06 | B7: 拿硬币 | C7: https://leetcode.cn/problems/na-ying-bi/ | D7: 0 | E7: Algorithms | F7: 2 | G7: 0 | H7: Easy | I7: LCP 2020 Spring Solo Problem 1
A8: LCP 07 | B8: 传递信息 | C8: https://leetcode.cn/problems/chuan-di-xin-xi/ | D8: 0 | E8: Algorithms | F8: 4 | G8: 0 | H8: Easy | I8: LCP 2020 Spring Solo Problem 2
A9: LCP 08 | B9: 剧情触发时间 | C9: https://leetcode.cn/problems/ju-qing-hong-fa-shi-jian/ | D9: 0 | E9: Algorithms | F9: 7 | G9: 0 | H9: Medium | I9: LCP 2020 Spring Solo Problem 3
A10: LCP 09 | B10: 最小跳跃次数 | C10: https://leetcode.cn/problems/zui-xiao-tiao-yue-ci-shu/ | D10: 0 | E10: Algorithms | F10: 8 | G10: 0 | H10: Hard | I10: LCP 2020 Spring Solo Problem 4
A11: LCP 10 | B11: 二叉树任务调度 | C11: https://leetcode.cn/problems/er-cha-shu-ren-wu-diao-du/ | D11: 0 | E11: Algorithms | F11: 10 | G11: 0 | H11: Hard | I11: LCP 2020 Spring Solo Problem 5
A12: LCP 11 | B12: 期望个数统计 | C12: https://leetcode.cn/problems/qi-wang-ge-shu-tong-ji/ | D12: 0 | E12: Algorithms | F12: 3 | G12: 0 | H12: Easy | I12: LCP 2020 Spring Team Problem 1
A13: LCP 12 | B13: 小张刷题计划 | C13: https://leetcode.cn/problems/xiao-zhang-shua-ti-ji-hua/ | D13: 0 | E13: Algorithms | F13: 6 | G13: 0 | H13: Medium | I13: LCP 2020 Spring Team Problem 2
... A83: LCP 82 | B83: 万灵之树 | C83: https://leetcode.cn/problems/cnHoX6/ | D83: 0 | E83: Algorithms | F83: 11 | G83: 0 | H83: Hard | I83: LCP 2023 Spring Team Problem 6

Sheet LCS
A1: # | B1: 标题 | C1: 链接 | D1: 是否会员 | E1: 分类 | F1: 等级 | G1: 进阶等级 | H1: 难度
A2: LCS 01 | B2: 下载插件 | C2: https://leetcode.cn/problems/Ju9Xwi/ | D2: 0 | E2: Algorithms | F2: 3 | G2: 0 | H2: Easy
A3: LCS 02 | B3: 完成一半题目 | C3: https://leetcode.cn/problems/WqXACV/ | D3: 0 | E3: Algorithms | F3: 3 | G3: 0 | H3: Easy
A4: LCS 03 | B4: 主题空间 | C4: https://leetcode.cn/problems/YesdPw/ | D4: 0 | E4: Algorithms | F4: 5 | G4: 0 | H4: Medium

Sheet 剑指Offer
A1: # | B1: 标题 | C1: 链接 | D1: 等级 | E1: 难度
A2: 3 | B2: 数组中重复的数字 | C2: https://leetcode.cn/problems/shu-zu-zhong-zhong-fu-de-shu-zi-lcof/ | D2: 3 | E2: Easy
A3: 4 | B3: 二维数组中的查找 | C3: https://leetcode.cn/problems/er-wei-shu-zu-zhong-de-cha-zhao-lcof/ | D3: 5 | E3: Medium
A4: 5 | B4: 替换空格 | C4: https://leetcode.cn/problems/ti-huan-kong-ge-lcof/ | D4: 3 | E4: Easy
A5: 6 | B5: 从尾到头打印链表 | C5: https://leetcode.cn/problems/cong-wei-dao-tou-da-yin-lian-biao-lcof/ | D5: 3 | E5: Easy
A6: 7 | B6: 重建二叉树 | C6: https://leetcode.cn/problems/zhong-jian-er-cha-shu-lcof/ | D6: 5 | E6: Medium
A7: 9 | B7: 用两个栈实现队列 | C7: https://leetcode.cn/problems/yong-liang-ge-zhan-shi-xian-dui-lie-lcof/ | D7: 4 | E7: Easy
A8: 10-I | B8: 斐波那契数列 | C8: https://leetcode.cn/problems/fei-bo-na-qi-shu-lie-lcof/ | D8: 2 | E8: Easy
A9: 10-II | B9: 青蛙跳台阶问题 | C9: https://leetcode.cn/problems/qing-wa-tiao-tai-jie-wen-ti-lcof/ | D9: 2 | E9: Easy
A10: 11 | B10: 旋转数组的最小数字 | C10: https://leetcode.cn/problems/xuan-zhuan-shu-zu-de-zui-xiao-shu-zi-lcof/ | D10: 6 | E10: Easy
A11: 12 | B11: 矩阵中的路径 | C11: https://leetcode.cn/problems/ju-zhen-zhong-de-lu-jing-lcof/ | D11: 4 | E11: Medium
A12: 13 | B12: 机器人的运动范围 | C12: https://leetcode.cn/problems/ji-qi-ren-de-yun-dong-fan-wei-lcof/ | D12: 4 | E12: Medium
A13: 14-I | B13: 剪绳子 | C13: https://leetcode.cn/problems/jian-sheng-zi-lcof/ | D13: 4 | E13: Medium
A14: 14-II | B14: 剪绳子 II | C14: https://leetcode.cn/problems/jian-sheng-zi-ii-lcof/ | D14: 4 | E14: Medium
A15: 15 | B15: 二进制中1的个数 | C15: https://leetcode.cn/problems/er-jin-zhi-zhong-1de-ge-shu-lcof/ | D15: 2 | E15: Easy
A16: 16 | B16: 数值的整数次方 | C16: https://leetcode.cn/problems/shu-zhi-de-zheng-shu-ci-fang-lcof/ | D16: 5 | E16: Medium
A17: 17 | B17: 打印从1到最大的n位数 | C17: https://leetcode.cn/problems/da-yin-cong-1dao-zui-da-de-nwei-shu-lcof/ | D17: 3 | E17: Easy
A18: 18 | B18: 删除链表的节点 | C18: https://leetcode.cn/problems/shan-chu-lian-biao-de-jie-dian-lcof/ | D18: 3 | E18: Easy
A19: 19 | B19: 正则表达式匹配 | C19: https://leetcode.cn/problems/zheng-ze-biao-da-shi-pi-pei-lcof/ | D19: 8 | E19: Hard
A20: 20 | B20: 表示数值的字符串 | C20: https://leetcode.cn/problems/biao-shi-shu-zhi-de-zi-fu-chuan-lcof/ | D20: 8 | E20: Medium
A21: 21 | B21: 调整数组顺序使奇数位于偶数前面 | C21: https://leetcode.cn/problems/diao-zheng-shu-zu-shun-xu-shi-qi-shu-wei-yu-ou-shu-qian-mian-lcof/ | D21: 3 | E21: Easy
A22: 22 | B22: 链表中倒数第k个节点 | C22: https://leetcode.cn/problems/lian-biao-zhong-dao-shu-di-kge-jie-dian-lcof/ | D22: 2 | E22: Easy
A23: 24 | B23: 反转链表 | C23: https://leetcode.cn/problems/fan-zhuan-lian-biao-lcof/ | D23: 3 | E23: Easy
A24: 25 | B24: 合并两个排序的链表 | C24: https://leetcode.cn/problems/he-bing-liang-ge-pai-xu-de-lian-biao-lcof/ | D24: 3 | E24: Easy
A25: 26 | B25: 树的子结构 | C25: https://leetcode.cn/problems/shu-de-zi-jie-gou-lcof/ | D25: 4 | E25: Medium
A26: 27 | B26: 二叉树的镜像 | C26: https://leetcode.cn/problems/er-cha-shu-de-jing-xiang-lcof/ | D26: 3 | E26: Easy
... A30: 31 | B30: 栈的压入、弹出序列 | C30: https://leetcode.cn/problems/zhan-de-ya-ru-dan-chu-xu-lie-lcof/ | D30: 5 | E30: Medium
A31: 32-I | B31: 从上到下打印二叉树 | C31: https://leetcode.cn/problems/cong-shang-dao-xia-da-yin-er-cha-shu-lcof/ | D31: 3 | E31: Medium
A32: 32-II | B32: 从上到下打印二叉树 II | C32: https://leetcode.cn/problems/cong-shang-dao-xia-da-yin-er-cha-shu-ii-lcof/ | D32: 4 | E32: Easy
A33: 32-III | B33: 从上到下打印二叉树 III | C33: https://leetcode.cn/problems/cong-shang-dao-xia-da-yin-er-cha-shu-iii-lcof/ | D33: 4 | E33: Medium
A34: 33 | B34: 二叉搜索树的后序遍历序列 | C34: https://leetcode.cn/problems/er-cha-sou-suo-shu-de-hou-xu-bian-li-xu-lie-lcof/ | D34: 6 | E34: Medium
A35: 34 | B35: 二叉树中和为某一值的路径 | C35: https://leetcode.cn/problems/er-cha-shu-zhong-he-wei-mou-yi-zhi-de-lu-jing-lcof/ | D35: 4 | E35: Medium
A36: 35 | B36: 复杂链表的复制 | C36: https://leetcode.cn/problems/fu-za-lian-biao-de-fu-zhi-lcof/ | D36: 6 | E36: Medium
A37: 36 | B37: 二叉搜索树与双向链表 | C37: https://leetcode.cn/problems/er-cha-sou-suo-shu-yu-shuang-xiang-lian-biao-lcof/ | D37: 4 | E37: Medium
A38: 37 | B38: 序列化二叉树 | C38: https://leetcode.cn/problems/xu-lie-hua-er-cha-shu-lcof/ | D38: 8 | E38: Hard
A39: 38 | B39: 字符串的排列 | C39: https://leetcode.cn/problems/zi-fu-chuan-de-pai-lie-lcof/ | D39: 5 | E39: Medium
A40: 39 | B40: 数组中出现次数超过一半的数字 | C40: https://leetcode.cn/problems/shu-zu-zhong-chu-xian-ci-shu-chao-guo-yi-ban-de-shu-zi-lcof/ | D40: 2 | E40: Easy
A41: 40 | B41: 最小的k个数 | C41: https://leetcode.cn/problems/zui-xiao-de-kge-shu-lcof/ | D41: 3 | E41: Easy
A42: 41 | B42: 数据流中的中位数 | C42: https://leetcode.cn/problems/shu-ju-liu-zhong-de-zhong-wei-shu-lcof/ | D42: 6 | E42: Hard
A43: 42 | B43: 连续子数组的最大和 | C43: https://leetcode.cn/problems/lian-xu-zi-shu-zu-de-zui-da-he-lcof/ | D43: 3 | E43: Easy
A44: 43 | B44: 1～n整数中1出现的次数 | C44: https://leetcode.cn/problems/1nzheng-shu-zhong-1chu-xian-de-ci-shu-lcof/ | D44: 8 | E44: Hard
A45: 44 | B45: 数字序列中某一位的数字 | C45: https://leetcode.cn/problems/shu-zi-xu-lie-zhong-mou-yi-wei-de-shu-zi-lcof/ | D45: 6 | E45: Medium
... A53: 52 | B53: 两个链表的第一个公共节点 | C53: https://leetcode.cn/problems/liang-ge-lian-biao-de-di-yi-ge-gong-gong-jie-dian-lcof/ | D53: 2 | E53: Easy
A54: 53-I | B54: 在排序数组中查找数字 I | C54: https://leetcode.cn/problems/zai-pai-xu-shu-zu-zhong-cha-zhao-shu-zi-lcof/ | D54: 4 | E54: Easy
A55: 53-II | B55: 0～n-1中缺失的数字 | C55: https://leetcode.cn/problems/que-shi-de-shu-zi-lcof/ | D55: 2 | E55: Easy
A56: 54 | B56: 二叉搜索树的第k大节点 | C56: https://leetcode.cn/problems/er-cha-sou-suo-shu-de-di-kda-jie-dian-lcof/ | D56: 3 | E56: Easy
A57: 55-I | B57: 二叉树的深度 | C57: https://leetcode.cn/problems/er-cha-shu-de-shen-du-lcof/ | D57: 3 | E57: Easy
A58: 55-II | B58: 平衡二叉树 | C58: https://leetcode.cn/problems/ping-heng-er-cha-shu-lcof/ | D58: 4 | E58: Easy
A59: 56-I | B59: 数组中数字出现的次数 | C59: https://leetcode.cn/problems/shu-zu-zhong-shu-zi-chu-xian-de-ci-shu-lcof/ | D59: 6 | E59: Medium
A60: 56-II | B60: 数组中数字出现的次数 II | C60: https://leetcode.cn/problems/shu-zu-zhong-shu-zi-chu-xian-de-ci-shu-ii-lcof/ | D60: 6 | E60: Medium
A61: 57 | B61: 和为s的两个数字 | C61: https://leetcode.cn/problems/he-wei-sde-liang-ge-shu-zi-lcof/ | D61: 3 | E61: Easy
A62: 57-II | B62: 和为s的连续正数序列 | C62: https://leetcode.cn/problems/he-wei-sde-lian-xu-zheng-shu-xu-lie-lcof/ | D62: 6 | E62: Easy
A63: 58-I | B63: 翻转单词顺序 | C63: https://leetcode.cn/problems/fan-zhuan-dan-ci-shun-xu-lcof/ | D63: 4 | E63: Easy
A64: 58-II | B64: 左旋转字符串 | C64: https://leetcode.cn/problems/zuo-xuan-zhuan-zi-fu-chuan-lcof/ | D64: 3 | E64: Easy
A65: 59-I | B65: 滑动窗口的最大值 | C65: https://leetcode.cn/problems/hua-dong-chuang-kou-de-zui-da-zhi-lcof/ | D65: 6 | E65: Hard
A66: 59-II | B66: 队列的最大值 | C66: https://leetcode.cn/problems/dui-lie-de-zui-da-zhi-lcof/ | D66: 7 | E66: Medium
A67: 60 | B67: n个骰子的点数 | C67: https://leetcode.cn/problems/nge-tou-zi-de-dian-shu-lcof/ | D67: 6 | E67: Medium
A68: 61 | B68: 扑克牌中的顺子 | C68: https://leetcode.cn/problems/bu-ke-pai-zhong-de-shun-zi-lcof/ | D68: 3 | E68: Easy
A69: 62 | B69: 圆圈中最后剩下的数字 | C69: https://leetcode.cn/problems/yuan-quan-zhong-zui-hou-sheng-xia-de-shu-zi-lcof/ | D69: 6 | E69: Easy
A70: 63 | B70: 股票的最大利润 | C70: https://leetcode.cn/problems/gu-piao-de-zui-da-li-run-lcof/ | D70: 3 | E70: Medium
A71: 64 | B71: 求1+2+…+n | C71: https://leetcode.cn/problems/qiu-12n-lcof/ | D71: 8 | E71: Medium
A72: 65 | B72: 不用加减乘除做加法 | C72: https://leetcode.cn/problems/bu-yong-jia-jian-cheng-chu-zuo-jia-fa-lcof/ | D72: 3 | E72: Easy
A73: 66 | B73: 构建乘积数组 | C73: https://leetcode.cn/problems/gou-jian-cheng-ji-shu-zu-lcof/ | D73: 5 | E73: Medium
A74: 67 | B74: 把字符串转换成整数 | C74: https://leetcode.cn/problems/ba-zi-fu-chuan-zhuan-huan-cheng-zheng-shu-lcof/ | D74: 6 | E74: Medium
A75: 68-I | B75: 二叉搜索树的最近公共祖先 | C75: https://leetcode.cn/problems/er-cha-sou-suo-shu-de-zui-jin-gong-gong-zu-xian-lcof/ | D75: 3 | E75: Easy
A76: 68-II | B76: 二叉树的最近公共祖先 | C76: https://leetcode.cn/problems/er-cha-shu-de-zui-jin-gong-gong-zu-xian-lcof/ | D76: 5 | E76: Easy

Sheet 剑指Offer专项突破版
A1: # | B1: 标题 | C1: 链接 | D1: 等级 | E1: 进阶等级 | F1: 难度
A2: 1 | B2: 整数除法 | C2: https://leetcode.cn/problems/xoh6Oh/ | D2: =主站!G30 -> 6 | E2: =主站!H30 -> 0 | F2: Easy
A3: 2 | B3: 二进制加法 | C3: https://leetcode.cn/problems/JFETK5/ | D3: =主站!G68 -> 3 | E3: =主站!H68 -> 0 | F3: Easy
A4: 3 | B4: 前 n 个数字二进制中 1 的个数 | C4: https://leetcode.cn/problems/w3tCBm/ | D4: =主站!G339 -> 2 | E4: =主站!H339 -> 5 | F4: Easy
A5: 4 | B5: 只出现一次的数字 | C5: https://leetcode.cn/problems/WGki4K/ | D5: =主站!G138 -> 6 | E5: =主站!H138 -> 0 | F5: Medium
A6: 5 | B6: 单词长度的最大乘积 | C6: https://leetcode.cn/problems/aseY1I/ | D6: =主站!G319 -> 4 | E6: =主站!H319 -> 0 | F6: Medium
A7: 6 | B7: 排序数组中两个数字之和 | C7: https://leetcode.cn/problems/kLl5u1/ | D7: =主站!G168 -> 3 | E7: =主站!H168 -> 0 | F7: Easy
A8: 7 | B8: 数组中和为 0 的三个数 | C8: https://leetcode.cn/problems/1fGaJU/ | D8: =主站!G16 -> 4 | E8: =主站!H16 -> 0 | F8: Medium
A9: 8 | B9: 和大于等于 target 的最短子数组 | C9: https://leetcode.cn/problems/2VG8Kg/ | D9: =主站!G210 -> 5 | E9: =主站!H210 -> 5 | F9: Medium
A10: 9 | B10: 乘积小于 K 的子数组 | C10: https://leetcode.cn/problems/ZVAVXX/ | D10: =主站!G714 -> 5 | E10: =主站!H714 -> 0 | F10: Medium
A11: 10 | B11: 和为 k 的子数组 | C11: https://leetcode.cn/problems/QTMn0o/ | D11: =主站!G561 -> 5 | E11: =主站!H561 -> 0 | F11: Medium
A12: 11 | B12: 0 和 1 个数相同的子数组 | C12: https://leetcode.cn/problems/A1NYOS/ | D12: =主站!G526 -> 5 | E12: =主站!H526 -> 0 | F12: Medium
A13: 12 | B13: 左右两边子数组的和相等 | C13: https://leetcode.cn/problems/tvdfij/ | D13: =主站!G725 -> 3 | E13: =主站!H725 -> 0 | F13: Easy
A14: 13 | B14: 二维子矩阵的和 | C14: https://leetcode.cn/problems/O4NDxx/ | D14: =主站!G305 -> 5 | E14: =主站!H305 -> 0 | F14: Medium
A15: 14 | B15: 字符串中的变位词 | C15: https://leetcode.cn/problems/MPnaiL/ | D15: =主站!G568 -> 4 | E15: =主站!H568 -> 0 | F15: Medium
A16: 15 | B16: 字符串中的所有变位词 | C16: https://leetcode.cn/problems/VabMRr/ | D16: =主站!G439 -> 4 | E16: =主站!H439 -> 0 | F16: Medium
A17: 16 | B17: 不含重复字符的最长子字符串 | C17: https://leetcode.cn/problems/wtcaE1/ | D17: =主站!G4 -> 5 | E17: =主站!H4 -> 0 | F17: Medium
A18: 17 | B18: 含有所有字符的最短字符串 | C18: https://leetcode.cn/problems/M1oyTv/ | D18: =主站!G77 -> 6 | E18: =主站!H77 -> 6 | F18: Hard
A19: 18 | B19: 有效的回文 | C19: https://leetcode.cn/problems/XltzEq/ | D19: =主站!G126 -> 3 | E19: =主站!H126 -> 0 | F19: Easy
A20: 19 | B20: 最多删除一个字符得到回文 | C20: https://leetcode.cn/problems/RQku0D/ | D20: =主站!G681 -> 3 | E20: =主站!H681 -> 0 | F20: Easy
A21: 20 | B21: 回文子字符串的个数 | C21: https://leetcode.cn/problems/a7VOhD/ | D21: =主站!G648 -> 5 | E21: =主站!H648 -> 0 | F21: Medium
A22: 21 | B22: 删除链表的倒数第 n 个结点 | C22: https://leetcode.cn/problems/SLwz0R/ | D22: =主站!G20 -> 3 | E22: =主站!H20 -> 4 | F22: Medium
A23: 22 | B23: 链表中环的入口节点 | C23: https://leetcode.cn/problems/c32eOV/ | D23: =主站!G143 -> 2 | E23: =主站!H143 -> 6 | F23: Medium
A24: 23 | B24: 两个链表的第一个重合节点 | C24: https://leetcode.cn/problems/3u1WK4/ | D24: =主站!G161 -> 2 | E24: =主站!H161 -> 4 | F24: Easy
A25: 24 | B25: 反转链表 | C25: https://leetcode.cn/problems/UHnkqh/ | D25: =主站!G207 -> 3 | E25: =主站!H207 -> 4 | F25: Easy
A26: 25 | B26: 链表中的两数相加 | C26: https://leetcode.cn/problems/lMSNwu/ | D26: =主站!G446 -> 4 | E26: =主站!H446 -> 4 | F26: Medium
A27: 26 | B27: 重排链表 | C27: https://leetcode.cn/problems/LGjMqU/ | D27: =主站!G144 -> 5 | E27: =主站!H144 -> 0 | F27: Medium
A28: 27 | B28: 回文链表 | C28: https://leetcode.cn/problems/aMhZSa/ | D28: =主站!G235 -> 3 | E28: =主站!H235 -> 5 | F28: Easy
A29: 28 | B29: 展平多级双向链表 | C29: https://leetcode.cn/problems/Qv1Da2/ | D29: =主站!G431 -> 7 | E29: =主站!H431 -> 0 | F29: Medium
A30: 29 | B30: 排序的循环链表 | C30: https://leetcode.cn/problems/4ueAj6/ | D30: =主站!G709 -> 5 | E30: =主站!H709 -> 0 | F30: Medium
A31: 30 | B31: 插入、删除和随机访问都是 O(1) 的容器 | C31: https://leetcode.cn/problems/FortPu/ | D31: =主站!G381 -> 6 | E31: =主站!H381 -> 0 | F31: Medium
A32: 31 | B32: 最近最少使用缓存 | C32: https://leetcode.cn/problems/OrIXps/ | D32: =主站!G147 -> 7 | E32: =主站!H147 -> 0 | F32: Medium
A33: 32 | B33: 有效的变位词 | C33: https://leetcode.cn/problems/dKk3P7/ | D33: =主站!G243 -> 2 | E33: =主站!H243 -> 3 | F33: Easy
A34: 33 | B34: 变位词组 | C34: https://leetcode.cn/problems/sfvd7V/ | D34: =主站!G50 -> 4 | E34: =主站!H50 -> 0 | F34: Medium
A35: 34 | B35: 外星语言是否排序 | C35: https://leetcode.cn/problems/lwyVBB/ | D35: =主站!G954 -> 3 | E35: =主站!H954 -> 0 | F35: Easy
A36: 35 | B36: 最小时间差 | C36: https://leetcode.cn/problems/569nqc/ | D36: =主站!G540 -> 3 | E36: =主站!H540 -> 0 | F36: Medium
A37: 36 | B37: 后缀表达式 | C37: https://leetcode.cn/problems/8Zf90G/ | D37: =主站!G151 -> 4 | E37: =主站!H151 -> 0 | F37: Medium
A38: 37 | B38: 小行星碰撞 | C38: https://leetcode.cn/problems/XagZNi/ | D38: =主站!G736 -> 5 | E38: =主站!H736 -> 0 | F38: Medium
A39: 38 | B39: 每日温度 | C39: https://leetcode.cn/problems/iIQa4I/ | D39: =主站!G740 -> 6 | E39: =主站!H740 -> 0 | F39: Medium
A40: 39 | B40: 直方图最大矩形面积 | C40: https://leetcode.cn/problems/0ynMMM/ | D40: =主站!G85 -> 7 | E40: =主站!H85 -> 0 | F40: Hard
A41: 40 | B41: 矩阵中最大的矩形 | C41: https://leetcode.cn/problems/PLYXKQ/ | D41: =主站!G86 -> 8 | E41: =主站!H86 -> 0 | F41: Hard
A42: 41 | B42: 滑动窗口的平均值 | C42: https://leetcode.cn/problems/qIsx9U/ | D42: =主站!G347 -> 3 | E42: =主站!H347 -> 0 | F42: Easy
A43: 42 | B43: 最近请求次数 | C43: https://leetcode.cn/problems/H8086Q/ | D43: =主站!G934 -> 3 | E43: =主站!H934 -> 0 | F43: Easy
A44: 43 | B44: 往完全二叉树添加节点 | C44: https://leetcode.cn/problems/NaqhDT/ | D44: =主站!G920 -> 6 | E44: =主站!H920 -> 0 | F44: Medium
A45: 44 | B45: 二叉树每层的最大值 | C45: https://leetcode.cn/problems/hPov7L/ | D45: =主站!G516 -> 4 | E45: =主站!H516 -> 0 | F45: Medium
A46: 45 | B46: 二叉树最底层最左边的值 | C46: https://leetcode.cn/problems/LwUNpT/ | D46: =主站!G514 -> 4 | E46: =主站!H514 -> 0 | F46: Medium
A47: 46 | B47: 二叉树的右侧视图 | C47: https://leetcode.cn/problems/WNC0Lk/ | D47: =主站!G200 -> 4 | E47: =主站!H200 -> 0 | F47: Medium
A48: 47 | B48: 二叉树剪枝 | C48: https://leetcode.cn/problems/pOCWxh/ | D48: =主站!G815 -> 4 | E48: =主站!H815 -> 0 | F48: Medium
A49: 48 | B49: 序列化与反序列化二叉树 | C49: https://leetcode.cn/problems/h54YBf/ | D49: =主站!G298 -> 8 | E49: =主站!H298 -> 0 | F49: Hard
A50: 49 | B50: 从根节点到叶节点的路径数字之和 | C50: https://leetcode.cn/problems/3Etpl5/ | D50: =主站!G130 -> 4 | E50: =主站!H130 -> 0 | F50: Medium
A51: 50 | B51: 向下的路径节点之和 | C51: https://leetcode.cn/problems/6eUYwP/ | D51: =主站!G438 -> 5 | E51: =主站!H438 -> 0 | F51: Medium
A52: 51 | B52: 节点之和最大的路径 | C52: https://leetcode.cn/problems/jC7MId/ | D52: =主站!G125 -> 6 | E52: =主站!H125 -> 0 | F52: Hard
A53: 52 | B53: 展平二叉搜索树 | C53: https://leetcode.cn/problems/NYBBNL/ | D53: =主站!G898 -> 3 | E53: =主站!H898 -> 0 | F53: Easy
A54: 53 | B54: 二叉搜索树中的中序后继 | C54: https://leetcode.cn/problems/P5rCT8/ | D54: =主站!G286 -> 5 | E54: =主站!H286 -> 0 | F54: Medium
A55: 54 | B55: 所有大于等于节点的值之和 | C55: https://leetcode.cn/problems/w6cpku/ | D55: =主站!G539 -> 4 | E55: =主站!H539 -> 0 | F55: Medium
A56: 55 | B56: 二叉搜索树迭代器 | C56: https://leetcode.cn/problems/kTOapQ/ | D56: =主站!G174 -> 4 | E56: =主站!H174 -> 7 | F56: Medium
A57: 56 | B57: 二叉搜索树中两个节点之和 | C57: https://leetcode.cn/problems/opLdQZ/ | D57: =主站!G654 -> 3 | E57: =主站!H654 -> 0 | F57: Easy
A58: 57 | B58: 值和下标之差都在给定的范围内 | C58: https://leetcode.cn/problems/7WqeDu/ | D58: =主站!G221 -> 6 | E58: =主站!H221 -> 0 | F58: Medium
A59: 58 | B59: 日程表 | C59: https://leetcode.cn/problems/fi9suh/ | D59: =主站!G730 -> 4 | E59: =主站!H730 -> 0 | F59: Medium
A60: 59 | B60: 数据流的第 K 大数值 | C60: https://leetcode.cn/problems/jBjn9C/ | D60: =主站!G704 -> 3 | E60: =主站!H704 -> 0 | F60: Easy
A61: 60 | B61: 出现频率最高的 k 个数字 | C61: https://leetcode.cn/problems/g5c51o/ | D61: =主站!G348 -> 3 | E61: =主站!H348 -> 6 | F61: Medium
A62: 61 | B62: 和最小的 k 个数对 | C62: https://leetcode.cn/problems/qn8gGX/ | D62: =主站!G374 -> 5 | E62: =主站!H374 -> 0 | F62: Medium
A63: 62 | B63: 实现前缀树 | C63: https://leetcode.cn/problems/QC3q1f/ | D63: =主站!G209 -> 5 | E63: =主站!H209 -> 0 | F63: Medium
A64: 63 | B64: 替换单词 | C64: https://leetcode.cn/problems/UhWRSj/ | D64: =主站!G649 -> 6 | E64: =主站!H649 -> 0 | F64: Medium
A65: 64 | B65: 神奇的字典 | C65: https://leetcode.cn/problems/US1pGT/ | D65: =主站!G677 -> 6 | E65: =主站!H677 -> 0 | F65: Medium
A66: 65 | B66: 最短的单词编码 | C66: https://leetcode.cn/problems/iSwD2y/ | D66: =主站!G821 -> 6 | E66: =主站!H821 -> 0 | F66: Medium
A67: 66 | B67: 单词之和 | C67: https://leetcode.cn/problems/z1R5dt/ | D67: =主站!G678 -> 7 | E67: =主站!H678 -> 0 | F67: Medium
A68: 67 | B68: 最大的异或 | C68: https://leetcode.cn/problems/ms70jA/ | D68: =主站!G422 -> 8 | E68: =主站!H422 -> 0 | F68: Medium
A69: 68 | B69: 查找插入位置 | C69: https://leetcode.cn/problems/N6YdxV/ | D69: =主站!G36 -> 2 | E69: =主站!H36 -> 0 | F69: Easy
A70: 69 | B70: 山峰数组的顶部 | C70: https://leetcode.cn/problems/B1IidL/ | D70: =主站!G853 -> 3 | E70: =主站!H853 -> 0 | F70: Easy
A71: 70 | B71: 排序数组中只出现一次的数字 | C71: https://leetcode.cn/problems/skFtm2/ | D71: =主站!G541 -> 4 | E71: =主站!H541 -> 0 | F71: Medium
A72: 71 | B72: 按权重生成随机数 | C72: https://leetcode.cn/problems/cuyjEf/ | D72: =主站!G529 -> 6 | E72: =主站!H529 -> 0 | F72: Medium
A73: 72 | B73: 求平方根 | C73: https://leetcode.cn/problems/jJ0w9p/ | D73: =主站!G70 -> 3 | E73: =主站!H70 -> 0 | F73: Easy
A74: 73 | B74: 狒狒吃香蕉 | C74: https://leetcode.cn/problems/nZZqjQ/ | D74: =主站!G876 -> 5 | E74: =主站!H876 -> 0 | F74: Medium
A75: 74 | B75: 合并区间 | C75: https://leetcode.cn/problems/SsGoHC/ | D75: =主站!G57 -> 5 | E75: =主站!H57 -> 0 | F75: Medium
A76: 75 | B76: 数组相对排序 | C76: https://leetcode.cn/problems/0H97ZC/ | D76: =主站!G1123 -> 3 | E76: =主站!H1123 -> 0 | F76: Easy
A77: 76 | B77: 数组中的第 k 大的数字 | C77: https://leetcode.cn/problems/xx4gT2/ | D77: =主站!G216 -> 6 | E77: =主站!H216 -> 0 | F77: Medium
A78: 77 | B78: 链表排序 | C78: https://leetcode.cn/problems/7WHec2/ | D78: =主站!G149 -> 6 | E78: =主站!H149 -> 8 | F78: Medium
A79: 78 | B79: 合并排序链表 | C79: https://leetcode.cn/problems/vvXgSW/ | D79: =主站!G24 -> 6 | E79: =主站!H24 -> 0 | F79: Hard
A80: 79 | B80: 所有子集 | C80: https://leetcode.cn/problems/TVdhkn/ | D80: =主站!G79 -> 4 | E80: =主站!H79 -> 0 | F80: Medium
A81: 80 | B81: 含有 k 个元素的组合 | C81: https://leetcode.cn/problems/uUsW3B/ | D81: =主站!G78 -> 4 | E81: =主站!H78 -> 0 | F81: Medium
A82: 81 | B82: 允许重复选择元素的组合 | C82: https://leetcode.cn/problems/Ygoe9J/ | D82: =主站!G40 -> 4 | E82: =主站!H40 -> 0 | F82: Medium
A83: 82 | B83: 含有重复元素集合的组合 | C83: https://leetcode.cn/problems/4sjJUc/ | D83: =主站!G41 -> 5 | E83: =主站!H41 -> 0 | F83: Medium
A84: 83 | B84: 没有重复元素集合的全排列 | C84: https://leetcode.cn/problems/VvJkup/ | D84: =主站!G47 -> 4 | E84: =主站!H47 -> 0 | F84: Medium
A85: 84 | B85: 含有重复元素集合的全排列 | C85: https://leetcode.cn/problems/7p8L0Z/ | D85: =主站!G48 -> 5 | E85: =主站!H48 -> 0 | F85: Medium
A86: 85 | B86: 生成匹配的括号 | C86: https://leetcode.cn/problems/IDBivT/ | D86: =主站!G23 -> 5 | E86: =主站!H23 -> 0 | F86: Medium
A87: 86 | B87: 分割回文子字符串 | C87: https://leetcode.cn/problems/M99OJA/ | D87: =主站!G132 -> 5 | E87: =主站!H132 -> 0 | F87: Medium
A88: 87 | B88: 复原 IP | C88: https://leetcode.cn/problems/0on3uN/ | D88: =主站!G94 -> 5 | E88: =主站!H94 -> 0 | F88: Medium
A89: 88 | B89: 爬楼梯的最少成本 | C89: https://leetcode.cn/problems/GzCJIP/ | D89: =主站!G747 -> 3 | E89: =主站!H747 -> 0 | F89: Easy
A90: 89 | B90: 房屋偷盗 | C90: https://leetcode.cn/problems/Gu0c2T/ | D90: =主站!G199 -> 3 | E90: =主站!H199 -> 0 | F90: Medium
A91: 90 | B91: 环形房屋偷盗 | C91: https://leetcode.cn/problems/PzWKhm/ | D91: =主站!G214 -> 4 | E91: =主站!H214 -> 0 | F91: Medium
A92: 91 | B92: 粉刷房子 | C92: https://leetcode.cn/problems/JEj789/ | D92: =主站!G257 -> 4 | E92: =主站!H257 -> 0 | F92: Medium
A93: 92 | B93: 翻转字符 | C93: https://leetcode.cn/problems/cyJERH/ | D93: =主站!G927 -> 5 | E93: =主站!H927 -> 0 | F93: Medium
A94: 93 | B94: 最长斐波那契数列 | C94: https://leetcode.cn/problems/Q91FMA/ | D94: =主站!G874 -> 7 | E94: =主站!H874 -> 0 | F94: Medium
A95: 94 | B95: 最少回文分割 | C95: https://leetcode.cn/problems/omKAoA/ | D95: =主站!G133 -> 6 | E95: =主站!H133 -> 0 | F95: Hard
A96: 95 | B96: 最长公共子序列 | C96: https://leetcode.cn/problems/qJnOS7/ | D96: =主站!G1144 -> 5 | E96: =主站!H1144 -> 0 | F96: Medium
A97: 96 | B97: 字符串交织 | C97: https://leetcode.cn/problems/IY6buf/ | D97: =主站!G98 -> 8 | E97: =主站!H98 -> 8 | F97: Medium
A98: 97 | B98: 子序列的数目 | C98: https://leetcode.cn/problems/21dk04/ | D98: =主站!G116 -> 7 | E98: =主站!H116 -> 0 | F98: Hard
A99: 98 | B99: 路径的数目 | C99: https://leetcode.cn/problems/2AoeFn/ | D99: =主站!G63 -> 4 | E99: =主站!H63 -> 0 | F99: Medium
A100: 99 | B100: 最小路径之和 | C100: https://leetcode.cn/problems/0i0mDW/ | D100: =主站!G65 -> 4 | E100: =主站!H65 -> 0 | F100: Medium
...

Sheet 程序员面试金典
A1: # | B1: 标题 | C1: 链接 | D1: 等级 | E1: 进阶等级 | F1: 难度
A2: 面试题 01.01 | B2: 判定字符是否唯一 | C2: https://leetcode.cn/problems/is-unique-lcci/ | D2: 2 | E2: 3 | F2: Easy
A3: 面试题 01.02 | B3: 判定是否互为字符重排 | C3: https://leetcode.cn/problems/check-permutation-lcci/ | D3: 2 | E3: 0 | F3: Easy
A4: 面试题 01.03 | B4: URL化 | C4: https://leetcode.cn/problems/string-to-url-lcci/ | D4: 3 | E4: 0 | F4: Easy
A5: 面试题 01.04 | B5: 回文排列 | C5: https://leetcode.cn/problems/palindrome-permutation-lcci/ | D5: 3 | E5: 0 | F5: Easy
A6: 面试题 01.05 | B6: 一次编辑 | C6: https://leetcode.cn/problems/one-away-lcci/ | D6: 4 | E6: 0 | F6: Medium
A7: 面试题 01.06 | B7: 字符串压缩 | C7: https://leetcode.cn/problems/compress-string-lcci/ | D7: 4 | E7: 0 | F7: Easy
A8: 面试题 01.07 | B8: 旋转矩阵 | C8: https://leetcode.cn/problems/rotate-matrix-lcci/ | D8: 5 | E8: 0 | F8: Medium
A9: 面试题 01.08 | B9: 零矩阵 | C9: https://leetcode.cn/problems/zero-matrix-lcci/ | D9: 3 | E9: 0 | F9: Medium
A10: 面试题 01.09 | B10: 字符串轮转 | C10: https://leetcode.cn/problems/string-rotation-lcci/ | D10: 3 | E10: 0 | F10: Easy
A11: 面试题 02.01 | B11: 移除重复节点 | C11: https://leetcode.cn/problems/remove-duplicate-node-lcci/ | D11: 3 | E11: 4 | F11: Easy
A12: 面试题 02.02 | B12: 返回倒数第 k 个节点 | C12: https://leetcode.cn/problems/kth-node-from-end-of-list-lcci/ | D12: 2 | E12: 0 | F12: Easy
A13: 面试题 02.03 | B13: 删除中间节点 | C13: https://leetcode.cn/problems/delete-middle-node-lcci/ | D13: 3 | E13: 0 | F13: Easy
... A110: 面试题 17.26 | B110: 稀疏相似度 | C110: https://leetcode.cn/problems/sparse-similarity-lcci/ | D110: 8 | E110: 0 | F110: Hard
